[
  {
    "type": "baseEffect",
    "effect": {
      "requirement": {
        "type": "distance",
        "minDistance": 1,
        "maxDistance": 1
      },
      "target": [
        {
          "value": 1,
          "areaType": false,
          "movement": -1,
          "constraints": []
        }
      ],
      "effects": [
        {
          "type": "moveToTarget"
        },
        {
          "type": "damage",
          "damage": 1,
          "marks": 2
        }
      ]
    }
  },

  {
    "type": "alternativeMode",
    "effect": {
      "additionalCost": ["Blue"],
      "requirement": {
        "type": "distance",
        "minDistance": 1,
        "maxDistance": 2
      },
      "target": [
        {
          "value": 2,
          "areaType": false,
          "movement": -1,
          "constraints": [
            "on same direction",
            "one target per square"
          ]
        }
      ],
      "effects": [
        {
          "type": "moveToTarget"
        },
        {
          "type": "damage",
          "damage": 2,
          "marks": 0
        }
      ]
    }
  }
]